XLXml/__init__.py
XLXml/converter.py
xlxml-1.0.0.dist-info/METADATA
xlxml-1.0.0.dist-info/WHEEL
xlxml-1.0.0.dist-info/top_level.txt
xlxml-1.0.0.dist-info/RECORD
